azure_transcribe/__init__.py
azure_transcribe/blob/__init__.py
azure_transcribe/blob/blob.py
azure_transcribe/fixtures/__init__.py
azure_transcribe/fixtures/azure_languages.py
azure_transcribe/fixtures/azure_transcribe_states.py
azure_transcribe/transcribe/__init__.py
azure_transcribe/transcribe/transcribe.py
azure_transcribe-0.5.dist-info/LICENSE
azure_transcribe-0.5.dist-info/METADATA
azure_transcribe-0.5.dist-info/WHEEL
azure_transcribe-0.5.dist-info/top_level.txt
azure_transcribe-0.5.dist-info/RECORD
